Workbook
Name APORTE_MENSAL: SIMULADOR!$B$5
Name PERFIL_INVESTIDOR: SIMULADOR!$B$8
Name PRAZO_INVESTIMENTO: SIMULADOR!$B$7

Sheet DASHBOARD
A1: PAINEL DE INVESTIMENTOS • FUNDOS IMOBILIÁRIOS
A19: VISÃO EXECUTIVA
A21: APORTE MENSAL | C21: PRAZO | E21: PATRIMÔNIO FINAL | G21: DIVIDENDOS/MÊS | I21: TOTAL INVESTIDO | K21: PERFIL
A22: =[0]!APORTE_MENSAL -> 1500 | C22: =[0]!PRAZO_INVESTIMENTO -> 1 | E22: =INDEX(EVOLUÇÃO!F:F,[0]!PRAZO_INVESTIMENTO*12+3) -> 18813.505 | G22: =INDEX(EVOLUÇÃO!G:G,[0]!PRAZO_INVESTIMENTO*12+3) -> 131.69454 | I22: =INDEX(EVOLUÇÃO!H:H,[0]!PRAZO_INVESTIMENTO*12+3) -> 18000 | K22: =SIMULADOR!B8 -> Agressivo
A24: CENÁRIOS DE PATRIMÔNIO | H24: RENDA MENSAL ESTIMADA
A25: Anos | B25: Patrimônio | C25: Dividendos/mês | H25: Indicador | I25: Valor
A26: 2 | B26: =FV(SIMULADOR!$G$4,A26*12,-SIMULADOR!$B$5,-SIMULADOR!$B$6) -> 39514.733 | C26: =B26*SIMULADOR!$G$5 -> 276.60313 | H26: Dividendos finais | I26: =INDEX(EVOLUÇÃO!G:G,SIMULADOR!B7*12+3) -> 131.69454
A27: 5 | B27: =FV(SIMULADOR!$G$4,A27*12,-SIMULADOR!$B$5,-SIMULADOR!$B$6) -> 114935.8 | C27: =B27*SIMULADOR!$G$5 -> 804.5506 | H27: Patrimônio necessário p/ meta | I27: =IF(SIMULADOR!G5=0,0,SIMULADOR!G7/SIMULADOR!G5) -> 714285.71
A28: 10 | B28: =FV(SIMULADOR!$G$4,A28*12,-SIMULADOR!$B$5,-SIMULADOR!$B$6) -> 300326.2 | C28: =B28*SIMULADOR!$G$5 -> 2102.2834 | H28: Aporte mensal p/ meta | I28: =SIMULADOR!H23 -> 0
A29: 20 | B29: =FV(SIMULADOR!$G$4,A29*12,-SIMULADOR!$B$5,-SIMULADOR!$B$6) -> 1081696.8 | C29: =B29*SIMULADOR!$G$5 -> 7571.8778 | H29: Rendimento mensal | I29: =SIMULADOR!G4 -> 0.008
A30: 30 | B30: =FV(SIMULADOR!$G$4,A30*12,-SIMULADOR!$B$5,-SIMULADOR!$B$6) -> 3114619.8 | C30: =B30*SIMULADOR!$G$5 -> 21802.339

Sheet SIMULADOR
A1: SIMULADOR DE INVESTIMENTOS EM FUNDOS IMOBILIÁRIOS
A3: DADOS DO INVESTIDOR | F3: PREMISSAS DA SIMULAÇÃO
A4: Renda mensal | B4: 5000 | C4: Valor de referência para planejamento. | F4: Rentabilidade média mensal | G4: 0.008 | H4: Crescimento total estimado da carteira por mês.
A5: Aporte mensal | B5: 1500 | C5: Quanto será investido todos os meses. | F5: Dividend Yield mensal | G5: 0.007 | H5: Estimativa média de proventos mensais sobre o patrimônio.
A6: Aporte inicial | B6: 0 | C6: Capital que já será aplicado no início. | F6: Reinvestir dividendos? | G6: Sim | H6: Se Sim, os dividendos são considerados no crescimento da carteira.
A7: Prazo do investimento (anos) | B7: 1 | C7: Horizonte de acumulação. | F7: Meta de renda mensal | G7: 5000 | H7: Renda mensal desejada com dividendos.
A8: Perfil de investidor | B8: Agressivo | C8: Usado para sugerir a distribuição por tipo de FII. | F8: Inflação estimada anual | G8: 0.04 | H8: Informativa; não descontada do resultado nominal.
A11: RESPOSTAS PRINCIPAIS
A13: QUANTO INVESTIR POR MÊS? | C13: POR QUANTOS ANOS? | E13: PATRIMÔNIO ACUMULADO
A14: =B5 -> 1500 | C14: =B7 -> 1 | E14: =INDEX(EVOLUÇÃO!F:F,B7*12+3) -> 18813.505
A17: DIVIDENDOS MENSAIS | C17: TOTAL INVESTIDO | E17: GANHO ACUMULADO
A18: =INDEX(EVOLUÇÃO!G:G,B7*12+3) -> 131.69454 | C18: =INDEX(EVOLUÇÃO!H:H,B7*12+3) -> 18000 | E18: =E14-C18 -> 813.50507
A21: META DE RENDA COM DIVIDENDOS
A23: Meta de dividendos/mês | B23: =G7 -> 5000 | D23: Patrimônio necessário | E23: =IF(G5=0,0,G7/G5) -> 714285.71 | G23: Aporte mensal necessário | H23: =IF(G5=0,0,MAX(0,-PMT(G4,B7*12,B6,-(G7/G5)))) -> 0
A26: Importante: os valores são projeções matemáticas, não promessa de rentabilidade. FIIs podem oscilar e dividendos podem variar.

Sheet EVOLUÇÃO
A1: EVOLUÇÃO MENSAL DA CARTEIRA
A3: Mês | B3: Ano | C3: Aporte | D3: Patrimônio inicial | E3: Rendimento | F3: Patrimônio final | G3: Dividendos estimados | H3: Total investido | I3: Ganho acumulado
A4: 1 | B4: =ROUNDUP(A4/12,0) -> 1 | C4: =IF(A4<=SIMULADOR!$B$7*12,SIMULADOR!$B$5,0) -> 1500 | D4: =SIMULADOR!$B$6 -> 0 | E4: =D4*SIMULADOR!$G$4 -> 0 | F4: =IF(A4<=SIMULADOR!$B$7*12,D4+E4+C4,0) -> 1500 | G4: =F4*SIMULADOR!$G$5 -> 10.5 | H4: =IF(A4<=SIMULADOR!$B$7*12,SIMULADOR!$B$6+C4,0) -> 1500 | I4: =F4-H4 -> 0
A5: 2 | B5: =ROUNDUP(A5/12,0) -> 1 | C5: =IF(A5<=SIMULADOR!$B$7*12,SIMULADOR!$B$5,0) -> 1500 | D5: =F4 -> 1500 | E5: =D5*SIMULADOR!$G$4 -> 12 | F5: =IF(A5<=SIMULADOR!$B$7*12,D5+E5+C5,0) -> 3012 | G5: =F5*SIMULADOR!$G$5 -> 21.084 | H5: =IF(A5<=SIMULADOR!$B$7*12,H4+C5,0) -> 3000 | I5: =F5-H5 -> 12
A6: 3 | B6: =ROUNDUP(A6/12,0) -> 1 | C6: =IF(A6<=SIMULADOR!$B$7*12,SIMULADOR!$B$5,0) -> 1500 | D6: =F5 -> 3012 | E6: =D6*SIMULADOR!$G$4 -> 24.096 | F6: =IF(A6<=SIMULADOR!$B$7*12,D6+E6+C6,0) -> 4536.096 | G6: =F6*SIMULADOR!$G$5 -> 31.752672 | H6: =IF(A6<=SIMULADOR!$B$7*12,H5+C6,0) -> 4500 | I6: =F6-H6 -> 36.096
A7: 4 | B7: =ROUNDUP(A7/12,0) -> 1 | C7: =IF(A7<=SIMULADOR!$B$7*12,SIMULADOR!$B$5,0) -> 1500 | D7: =F6 -> 4536.096 | E7: =D7*SIMULADOR!$G$4 -> 36.288768 | F7: =IF(A7<=SIMULADOR!$B$7*12,D7+E7+C7,0) -> 6072.3848 | G7: =F7*SIMULADOR!$G$5 -> 42.506693 | H7: =IF(A7<=SIMULADOR!$B$7*12,H6+C7,0) -> 6000 | I7: =F7-H7 -> 72.384768
A8: 5 | B8: =ROUNDUP(A8/12,0) -> 1 | C8: =IF(A8<=SIMULADOR!$B$7*12,SIMULADOR!$B$5,0) -> 1500 | D8: =F7 -> 6072.3848 | E8: =D8*SIMULADOR!$G$4 -> 48.579078 | F8: =IF(A8<=SIMULADOR!$B$7*12,D8+E8+C8,0) -> 7620.9638 | G8: =F8*SIMULADOR!$G$5 -> 53.346747 | H8: =IF(A8<=SIMULADOR!$B$7*12,H7+C8,0) -> 7500 | I8: =F8-H8 -> 120.96385
A9: 6 | B9: =ROUNDUP(A9/12,0) -> 1 | C9: =IF(A9<=SIMULADOR!$B$7*12,SIMULADOR!$B$5,0) -> 1500 | D9: =F8 -> 7620.9638 | E9: =D9*SIMULADOR!$G$4 -> 60.967711 | F9: =IF(A9<=SIMULADOR!$B$7*12,D9+E9+C9,0) -> 9181.9316 | G9: =F9*SIMULADOR!$G$5 -> 64.273521 | H9: =IF(A9<=SIMULADOR!$B$7*12,H8+C9,0) -> 9000 | I9: =F9-H9 -> 181.93156
A10: 7 | B10: =ROUNDUP(A10/12,0) -> 1 | C10: =IF(A10<=SIMULADOR!$B$7*12,SIMULADOR!$B$5,0) -> 1500 | D10: =F9 -> 9181.9316 | E10: =D10*SIMULADOR!$G$4 -> 73.455452 | F10: =IF(A10<=SIMULADOR!$B$7*12,D10+E10+C10,0) -> 10755.387 | G10: =F10*SIMULADOR!$G$5 -> 75.287709 | H10: =IF(A10<=SIMULADOR!$B$7*12,H9+C10,0) -> 10500 | I10: =F10-H10 -> 255.38701
A11: 8 | B11: =ROUNDUP(A11/12,0) -> 1 | C11: =IF(A11<=SIMULADOR!$B$7*12,SIMULADOR!$B$5,0) -> 1500 | D11: =F10 -> 10755.387 | E11: =D11*SIMULADOR!$G$4 -> 86.043096 | F11: =IF(A11<=SIMULADOR!$B$7*12,D11+E11+C11,0) -> 12341.43 | G11: =F11*SIMULADOR!$G$5 -> 86.390011 | H11: =IF(A11<=SIMULADOR!$B$7*12,H10+C11,0) -> 12000 | I11: =F11-H11 -> 341.43011
A12: 9 | B12: =ROUNDUP(A12/12,0) -> 1 | C12: =IF(A12<=SIMULADOR!$B$7*12,SIMULADOR!$B$5,0) -> 1500 | D12: =F11 -> 12341.43 | E12: =D12*SIMULADOR!$G$4 -> 98.731441 | F12: =IF(A12<=SIMULADOR!$B$7*12,D12+E12+C12,0) -> 13940.162 | G12: =F12*SIMULADOR!$G$5 -> 97.581131 | H12: =IF(A12<=SIMULADOR!$B$7*12,H11+C12,0) -> 13500 | I12: =F12-H12 -> 440.16155
A13: 10 | B13: =ROUNDUP(A13/12,0) -> 1 | C13: =IF(A13<=SIMULADOR!$B$7*12,SIMULADOR!$B$5,0) -> 1500 | D13: =F12 -> 13940.162 | E13: =D13*SIMULADOR!$G$4 -> 111.52129 | F13: =IF(A13<=SIMULADOR!$B$7*12,D13+E13+C13,0) -> 15551.683 | G13: =F13*SIMULADOR!$G$5 -> 108.86178 | H13: =IF(A13<=SIMULADOR!$B$7*12,H12+C13,0) -> 15000 | I13: =F13-H13 -> 551.68284
A14: 11 | B14: =ROUNDUP(A14/12,0) -> 1 | C14: =IF(A14<=SIMULADOR!$B$7*12,SIMULADOR!$B$5,0) -> 1500 | D14: =F13 -> 15551.683 | E14: =D14*SIMULADOR!$G$4 -> 124.41346 | F14: =IF(A14<=SIMULADOR!$B$7*12,D14+E14+C14,0) -> 17176.096 | G14: =F14*SIMULADOR!$G$5 -> 120.23267 | H14: =IF(A14<=SIMULADOR!$B$7*12,H13+C14,0) -> 16500 | I14: =F14-H14 -> 676.0963
A15: 12 | B15: =ROUNDUP(A15/12,0) -> 1 | C15: =IF(A15<=SIMULADOR!$B$7*12,SIMULADOR!$B$5,0) -> 1500 | D15: =F14 -> 17176.096 | E15: =D15*SIMULADOR!$G$4 -> 137.40877 | F15: =IF(A15<=SIMULADOR!$B$7*12,D15+E15+C15,0) -> 18813.505 | G15: =F15*SIMULADOR!$G$5 -> 131.69454 | H15: =IF(A15<=SIMULADOR!$B$7*12,H14+C15,0) -> 18000 | I15: =F15-H15 -> 813.50507
A16: 13 | B16: =ROUNDUP(A16/12,0) -> 2 | C16: =IF(A16<=SIMULADOR!$B$7*12,SIMULADOR!$B$5,0) -> 0 | D16: =F15 -> 18813.505 | E16: =D16*SIMULADOR!$G$4 -> 150.50804 | F16: =IF(A16<=SIMULADOR!$B$7*12,D16+E16+C16,0) -> 0 | G16: =F16*SIMULADOR!$G$5 -> 0 | H16: =IF(A16<=SIMULADOR!$B$7*12,H15+C16,0) -> 0 | I16: =F16-H16 -> 0
... A603: 600 | B603: =ROUNDUP(A603/12,0) -> 50 | C603: =IF(A603<=SIMULADOR!$B$7*12,SIMULADOR!$B$5,0) -> 0 | D603: =F602 -> 0 | E603: =D603*SIMULADOR!$G$4 -> 0 | F603: =IF(A603<=SIMULADOR!$B$7*12,D603+E603+C603,0) -> 0 | G603: =F603*SIMULADOR!$G$5 -> 0 | H603: =IF(A603<=SIMULADOR!$B$7*12,H602+C603,0) -> 0 | I603: =F603-H603 -> 0

Sheet PERFIL_FII
A1: PERFIS E DISTRIBUIÇÃO SUGERIDA DE FIIs
A3: TIPO DE FII | B3: CONSERVADOR | C3: MODERADO | D3: AGRESSIVO | F3: EXPLICAÇÃO
A4: Papel | B4: 0.3 | C4: 0.32 | D4: 0.5 | F4: Recebíveis imobiliários; tende a ter foco em crédito.
A5: Tijolo | B5: 0.5 | C5: 0.35 | D5: 0.1 | F5: Imóveis físicos geradores de renda, como lajes, galpões e shoppings.
A6: Híbridos | B6: 0.1 | C6: 0.08 | D6: 0.05 | F6: Combina estratégias de papel e tijolo.
A7: FOFs | B7: 0.1 | C7: 0.05 | D7: 0.05 | F7: Fundos que investem em outros FIIs.
A8: Desenvolvimento | B8: 0 | C8: 0.1 | D8: 0.2 | F8: Maior exposição a projetos e desenvolvimento imobiliário.
A9: Hotelarias | B9: 0 | C9: 0.1 | D9: 0.1 | F9: Exposição ao segmento hoteleiro e sua dinâmica operacional.
A11: TOTAL | B11: =SUM(B4:B9) -> 1 | C11: =SUM(C4:C9) -> 1 | D11: =SUM(D4:D9) -> 1
A14: Perfil selecionado | B14: =SIMULADOR!B8 -> Agressivo
A15: Aporte mensal | B15: =SIMULADOR!B5 -> 1500
A16: Conferência | B16: =IF(SUM(B11:D11)=300%,"OK","VERIFICAR") -> OK
A19: TIPO DE FII | B19: PERCENTUAL | C19: VALOR MENSAL
A20: Papel | B20: =IF(SIMULADOR!$B$8="Conservador",B4,IF(SIMULADOR!$B$8="Moderado",C4,D4)) -> 0.5 | C20: =SIMULADOR!$B$5*B20 -> 750
A21: Tijolo | B21: =IF(SIMULADOR!$B$8="Conservador",B5,IF(SIMULADOR!$B$8="Moderado",C5,D5)) -> 0.1 | C21: =SIMULADOR!$B$5*B21 -> 150
A22: Híbridos | B22: =IF(SIMULADOR!$B$8="Conservador",B6,IF(SIMULADOR!$B$8="Moderado",C6,D6)) -> 0.05 | C22: =SIMULADOR!$B$5*B22 -> 75
A23: FOFs | B23: =IF(SIMULADOR!$B$8="Conservador",B7,IF(SIMULADOR!$B$8="Moderado",C7,D7)) -> 0.05 | C23: =SIMULADOR!$B$5*B23 -> 75
A24: Desenvolvimento | B24: =IF(SIMULADOR!$B$8="Conservador",B8,IF(SIMULADOR!$B$8="Moderado",C8,D8)) -> 0.2 | C24: =SIMULADOR!$B$5*B24 -> 300
A25: Hotelarias | B25: =IF(SIMULADOR!$B$8="Conservador",B9,IF(SIMULADOR!$B$8="Moderado",C9,D9)) -> 0.1 | C25: =SIMULADOR!$B$5*B25 -> 150

Sheet BASE
A1: BASE DE REFERÊNCIA
A3: Indicador | B3: Valor | C3: Uso
A4: Rentabilidade mensal – referência | B4: 0.008 | C4: Premissa editável no SIMULADOR.
A5: Dividend Yield mensal – referência | B5: 0.007 | C5: Premissa editável no SIMULADOR.
A6: Aporte sugerido sobre renda | B6: 0.2 | C6: Referência de planejamento, não regra.
A7: Horizonte curto | B7: 5 | C7: Cenário.
A8: Horizonte médio | B8: 10 | C8: Cenário.
A9: Horizonte longo | B9: 20 | C9: Cenário.
